pylluminator/__init__.py
pylluminator/annotations.py
pylluminator/cnv.py
pylluminator/dm.py
pylluminator/mask.py
pylluminator/ml.py
pylluminator/quality_control.py
pylluminator/read_idat.py
pylluminator/sample_sheet.py
pylluminator/samples.py
pylluminator/stats.py
pylluminator/utils.py
pylluminator/visualizations.py
pylluminator-1.3.dist-info/licenses/LICENSE
pylluminator-1.3.dist-info/METADATA
pylluminator-1.3.dist-info/WHEEL
pylluminator-1.3.dist-info/top_level.txt
pylluminator-1.3.dist-info/RECORD
