Metadata-Version: 2.4
Name: pylluminator
Version: 1.3
Summary: Tool to preprocess, analyze and visualize DNA methylation data from Illumina micro-arrays
Author-email: Elio <elio.fanchon@univ-amu.fr>
Maintainer-email: Elio <elio.fanchon@univ-amu.fr>
License-Expression: MIT
Project-URL: Homepage, https://pylluminator.readthedocs.io/
Project-URL: Documentation, https://pylluminator.readthedocs.io/
Project-URL: Repository, https://github.com/eliopato/pylluminator
Project-URL: Issues, https://github.com/eliopato/pylluminator/issues
Keywords: dna-methylation,epigenetics,illumina,bioinformatics,microarray,methylation,DMR
Classifier: Development Status :: 5 - Production/Stable
Classifier: Programming Language :: Python :: 3.12
Classifier: Programming Language :: Python :: 3.13
Classifier: Intended Audience :: Developers
Classifier: Intended Audience :: Science/Research
Classifier: Topic :: Scientific/Engineering
Classifier: Topic :: Scientific/Engineering :: Bio-Informatics
Requires-Python: >=3.10
License-File: LICENSE
Requires-Dist: ailist==2.1.7
Requires-Dist: fastcluster==1.2.6
Requires-Dist: inmoose==0.8.1
Requires-Dist: joblib==1.5.2
Requires-Dist: KDEpy==1.1.12
Requires-Dist: linear_segment==1.2.1
Requires-Dist: matplotlib==3.10.6
Requires-Dist: notebook>=7.2.2
Requires-Dist: numpy<2.0.0
Requires-Dist: pandas<3.0.0,>=2.2.0
Requires-Dist: patsy==1.0.1
Requires-Dist: pyranges1==1.1.4
Requires-Dist: scikit-learn==1.7.2
Requires-Dist: scipy==1.15.3
Requires-Dist: statsmodels==0.14.5
Requires-Dist: seaborn==0.13.2
Provides-Extra: dev
Requires-Dist: coverage==7.10.6; extra == "dev"
Requires-Dist: pytest==8.4.2; extra == "dev"
Requires-Dist: build; extra == "dev"
Requires-Dist: twine; extra == "dev"
Provides-Extra: docs
Requires-Dist: sphinx==8.1.3; extra == "docs"
Requires-Dist: sphinx_rtd_theme; extra == "docs"
Requires-Dist: nbsphinx; extra == "docs"
Provides-Extra: gsea
Requires-Dist: gseapy==1.1.10; extra == "gsea"
Requires-Dist: networkx==3.5; extra == "gsea"
Dynamic: license-file
